main.py
notion.py
scraper.py
tmdb.py
notion_watchlist-0.2.1.dist-info/METADATA
notion_watchlist-0.2.1.dist-info/WHEEL
notion_watchlist-0.2.1.dist-info/entry_points.txt
notion_watchlist-0.2.1.dist-info/top_level.txt
notion_watchlist-0.2.1.dist-info/RECORD
