Metadata-Version: 2.4
Name: notion-watchlist
Version: 0.2.1
Summary: CLI tool for automating your movie & TV watchlist in Notion via TMDB and IMDb
Home-page: https://github.com/mathiramilo/notion-watchlist
Author: Mathias Ramilo
Author-email: mathiramilo2290@gmail.com
Requires-Dist: requests>=2.25.1
Requires-Dist: notion-client>=0.3.0
Requires-Dist: pyyaml>=5.4.1
Requires-Dist: beautifulsoup4>=4.9.3
Dynamic: author
Dynamic: author-email
Dynamic: home-page
Dynamic: requires-dist
Dynamic: summary
